{
	"track_name": "Imola",
	"race_type": "FormulaOne",
	"number_of_laps": 55,
	"positions": [
		{
			"name": "Gabriel Bezerra",
			"skill": 10,
			"tire_type": "Soft",
			"tire_condition": 1.0,
			"overtake": false 
		},
		{
			"name": "Daniel Sant'Anna",
			"skill": 9,
			"tire_type": "Medium",
			"tire_condition": 1.0,
			"overtake": true
		},
		{
			"name": "Letícia Oliveira",
			"skill": 8,
			"tire_type": "Hard",
			"tire_condition": 1.0,
			"overtake": true
		},
		{
			"name": "Luan Gadioli",
			"skill": 7,
			"tire_type": "Soft",
			"tire_condition": 1.0,
			"overtake": true
		},
		{
			"name": "Isabelle Rizzo",
			"skill": 6,
			"tire_type": "Medium",
			"tire_condition": 1.0,
			"overtake": true
		},
		{
			"name": "Thalles Rodrigues",
			"skill": 5,
			"tire_type": "Hard",
			"tire_condition": 1.0,
			"overtake": true
		}
	],
	"grid_setup": "AsIs"
}
